django_groot-0.1.1.dist-info/DESCRIPTION.rst
django_groot-0.1.1.dist-info/METADATA
django_groot-0.1.1.dist-info/RECORD
django_groot-0.1.1.dist-info/WHEEL
django_groot-0.1.1.dist-info/metadata.json
django_groot-0.1.1.dist-info/top_level.txt
groot/__init__.py
groot/actions.py
groot/admin.py
groot/apps.py
groot/forms.py
groot/migrations/__init__.py
groot/templates/admin/groot_change_form.html
groot/templates/admin/group_permissions.html
groot/templates/admin/update_permissions.html
